target_postgres/.gitignore
target_postgres/__init__.py
target_postgres/connector.py
target_postgres/driver.py
target_postgres/sinks.py
target_postgres/target.py
target_postgres/tests/__init__.py
target_postgres/tests/conftest.py
target_postgres/tests/core.py
target_postgres/tests/test_sdk.py
target_postgres/tests/test_target_postgres.py
target_postgres/tests/test_types.py
target_postgres/tests/data_files/array_data.singer
target_postgres/tests/data_files/base16_content_encoding_interpreted.singer
target_postgres/tests/data_files/base16_content_encoding_not_interpreted.singer
target_postgres/tests/data_files/camelcase.singer
target_postgres/tests/data_files/camelcase_complex_schema.singer
target_postgres/tests/data_files/commits.singer
target_postgres/tests/data_files/duplicate_records.singer
target_postgres/tests/data_files/encoded_strings.singer
target_postgres/tests/data_files/invalid_schema.singer
target_postgres/tests/data_files/jsonb_data.singer
target_postgres/tests/data_files/large_int.singer
target_postgres/tests/data_files/large_numeric_primary_key.singer
target_postgres/tests/data_files/missing_value.singer
target_postgres/tests/data_files/multiple_schema_messages.singer
target_postgres/tests/data_files/multiple_state_messages.singer
target_postgres/tests/data_files/new_array_column.singer
target_postgres/tests/data_files/optional_attributes.singer
target_postgres/tests/data_files/record_before_schema.singer
target_postgres/tests/data_files/record_missing_key_property.singer
target_postgres/tests/data_files/record_missing_required_property.singer
target_postgres/tests/data_files/reserved_keywords.singer
target_postgres/tests/data_files/schema_no_properties.singer
target_postgres/tests/data_files/schema_updates.singer
target_postgres/tests/data_files/special_chars_in_attributes.singer
target_postgres/tests/data_files/tap_aapl.singer
target_postgres/tests/data_files/tap_countries.singer
meltanolabs_target_postgres-0.6.0.dist-info/METADATA
meltanolabs_target_postgres-0.6.0.dist-info/WHEEL
meltanolabs_target_postgres-0.6.0.dist-info/entry_points.txt
meltanolabs_target_postgres-0.6.0.dist-info/licenses/LICENSE
meltanolabs_target_postgres-0.6.0.dist-info/RECORD
