Metadata-Version: 2.4
Name: meltanolabs-target-postgres
Version: 0.6.0
Summary: Singer target for Postgres, built with the Meltano SDK for Singer Targets.
Project-URL: Homepage, https://meltano.com
Project-URL: Repository, https://github.com/MeltanoLabs/target-postgres
Project-URL: Documentation, https://github.com/MeltanoLabs/target-postgres/blob/main/README.md
Author-email: Meltano Team and Contributors <hello@meltano.com>
Maintainer-email: Meltano Team and Contributors <hello@meltano.com>
License-Expression: MIT
License-File: LICENSE
Keywords: ELT,Meltano,Meltano SDK,Postgres,Singer
Classifier: Intended Audience :: Developers
Classifier: Operating System :: OS Independent
Classifier: Programming Language :: Python :: 3.10
Classifier: Programming Language :: Python :: 3.11
Classifier: Programming Language :: Python :: 3.12
Classifier: Programming Language :: Python :: 3.13
Classifier: Programming Language :: Python :: 3.14
Classifier: Programming Language :: Python :: Implementation :: CPython
Requires-Python: >=3.10
Requires-Dist: paramiko>=4
Requires-Dist: psycopg2-binary==2.9.10
Requires-Dist: psycopg[binary]==3.2.10
Requires-Dist: singer-sdk[sql]~=0.52.0
Requires-Dist: sqlalchemy~=2.0
Provides-Extra: faker
Requires-Dist: faker~=37.1; extra == 'faker'
